dsomit/__init__.py
dsomit/dsomit.py
dsomit-1.0.0.dist-info/METADATA
dsomit-1.0.0.dist-info/WHEEL
dsomit-1.0.0.dist-info/top_level.txt
dsomit-1.0.0.dist-info/RECORD
