Metadata-Version: 2.1
Name: dsomit
Version: 1.0.0
Summary: Removes all .DS_Store files from a list
Home-page: https://github.com/anjandash/dsomit
Author: anjandash
License: UNKNOWN
Platform: UNKNOWN
